py_uml_gen_gui.py
py_uml_gen_gui-0.0.1.dist-info/LICENSE
py_uml_gen_gui-0.0.1.dist-info/WHEEL
py_uml_gen_gui-0.0.1.dist-info/METADATA
py_uml_gen_gui-0.0.1.dist-info/RECORD
