Metadata-Version: 2.1
Name: py_uml_gen_gui
Version: 0.0.1
Summary: Python 🐍 UML diagrams generator GUI
Author-email: chaitu-ycr <chaiu.ycr@gmail.com>
Requires-Python: >=3.6
Classifier: Programming Language :: Python :: 3
Classifier: Programming Language :: Python :: 3.6
Classifier: Programming Language :: Python :: 3.9
Classifier: License :: OSI Approved :: MIT License
Classifier: Operating System :: Microsoft :: Windows
Requires-Dist: pylint
Requires-Dist: graphviz
Requires-Dist: PySimpleGUI
Project-URL: Home, https://github.com/chaitu-ycr/py_uml_gen_gui
